{
  "results": {
    "lastUpdate": "01 April 2026",
    "nextUpdate": "10 June 2026 (46 days)"
  },
  "buttons": [
    {
      "tag": "BUTTON",
      "text": "More",
      "class": "card-heading-tiny ff-mb-0 dropdown_dropupButton__3VUQ1\n                dropdown_noBorder__NXxB7 ",
      "visible": true,
      "rect": {
        "x": 1034.921875,
        "y": -1617.59375,
        "width": 81.328125,
        "height": 47,
        "top": -1617.59375,
        "right": 1116.25,
        "bottom": -1570.59375,
        "left": 1034.921875
      }
    },
    {
      "tag": "BUTTON",
      "text": "Show full rankings",
      "class": "button-module_withIcons__m1fXh fcds-button button-module_buttonTheme__uUWBc button-module_secondaryVariant__x-Sdk button-module_darkenOnHover__gFIEI",
      "visible": true,
      "rect": {
        "x": 521.328125,
        "y": 425.609375,
        "width": 237.328125,
        "height": 48,
        "top": 425.609375,
        "right": 758.65625,
        "bottom": 473.609375,
        "left": 521.328125
      }
    },
    {
      "tag": "A",
      "text": "More on how the Men's Ranking is calculated",
      "class": "",
      "visible": true,
      "rect": {
        "x": 82,
        "y": 1241.375,
        "width": 330.515625,
        "height": 20,
        "top": 1241.375,
        "right": 412.515625,
        "bottom": 1261.375,
        "left": 82
      }
    },
    {
      "tag": "A",
      "text": "FIFA/Coca-Cola Women's World Ranking\n\nSee latest status of the FIFA-Coca Cola Women's World Ranking\n\nRead more",
      "class": "link-module_link__F9IVG undefined",
      "visible": true,
      "rect": {
        "x": 82,
        "y": 2166.4375,
        "width": 546,
        "height": 596.90625,
        "top": 2166.4375,
        "right": 628,
        "bottom": 2763.34375,
        "left": 82
      }
    },
    {
      "tag": "A",
      "text": "Read more",
      "class": "link-module_link__F9IVG button-module_withIcons__m1fXh button-module_tertiaryLink__G5rFB fcds-button feature-card-module_link__1FK3s button-module_buttonTheme__uUWBc button-module_tertiaryVariant__eBPK- button-module_darkenOnHover__gFIEI",
      "visible": true,
      "rect": {
        "x": 50,
        "y": 2675.34375,
        "width": 176.21875,
        "height": 48,
        "top": 2675.34375,
        "right": 226.21875,
        "bottom": 2723.34375,
        "left": 50
      }
    },
    {
      "tag": "A",
      "text": "FIFA/Coca-Cola Women's World Ranking Procedures\n\nIn the FIFA Women's World Ranking (WWR) teams are ranked according to a value that is a measure of their actual strength. One of the benefits of this is that a considerable amount can be learned about the ranking value (or rating points) of a team.\n\nRead more",
      "class": "link-module_link__F9IVG undefined",
      "visible": true,
      "rect": {
        "x": 652,
        "y": 2166.4375,
        "width": 546,
        "height": 704.3125,
        "top": 2166.4375,
        "right": 1198,
        "bottom": 2870.75,
        "left": 652
      }
    },
    {
      "tag": "A",
      "text": "Read more",
      "class": "link-module_link__F9IVG button-module_withIcons__m1fXh button-module_tertiaryLink__G5rFB fcds-button feature-card-module_link__1FK3s button-module_buttonTheme__uUWBc button-module_tertiaryVariant__eBPK- button-module_darkenOnHover__gFIEI",
      "visible": true,
      "rect": {
        "x": 620,
        "y": 2782.75,
        "width": 176.21875,
        "height": 48,
        "top": 2782.75,
        "right": 796.21875,
        "bottom": 2830.75,
        "left": 620
      }
    },
    {
      "tag": "BUTTON",
      "text": "Show more",
      "class": "button-module_smallSize__I42VN button-module_withIcons__m1fXh fcds-button multiselect-filter-module_showMoreButton__Qa-HX button-module_buttonTheme__uUWBc button-module_tertiaryVariant__eBPK- button-module_darkenOnHover__gFIEI",
      "visible": true,
      "rect": {
        "x": 1304,
        "y": 443,
        "width": 124.046875,
        "height": 28,
        "top": 443,
        "right": 1428.046875,
        "bottom": 471,
        "left": 1304
      }
    },
    {
      "tag": "BUTTON",
      "text": "Show more",
      "class": "button-module_smallSize__I42VN button-module_withIcons__m1fXh fcds-button radio-group-filter-module_showMoreButton__rJgEB button-module_buttonTheme__uUWBc button-module_tertiaryVariant__eBPK- button-module_darkenOnHover__gFIEI",
      "visible": true,
      "rect": {
        "x": 1304,
        "y": 1357,
        "width": 124.046875,
        "height": 28,
        "top": 1357,
        "right": 1428.046875,
        "bottom": 1385,
        "left": 1304
      }
    },
    {
      "tag": "BUTTON",
      "text": "Show Purposes",
      "class": "",
      "visible": true,
      "rect": {
        "x": 1074.484375,
        "y": 628.5078125,
        "width": 125,
        "height": 41.609375,
        "top": 628.5078125,
        "right": 1199.484375,
        "bottom": 670.1171875,
        "left": 1074.484375
      }
    },
    {
      "tag": "A",
      "text": "More information",
      "class": "privacy-notice-link",
      "visible": false,
      "rect": {
        "x": 0,
        "y": 0,
        "width": 0,
        "height": 0,
        "top": 0,
        "right": 0,
        "bottom": 0,
        "left": 0
      }
    }
  ]
}